django_turnstile-0.1.3.dist-info/licenses/LICENSE
turnstile/__init__.py
turnstile/apps.py
turnstile/fields.py
turnstile/settings.py
turnstile/widgets.py
turnstile/migrations/__init__.py
turnstile/templates/turnstile/forms/widgets/turnstile_widget.html
django_turnstile-0.1.3.dist-info/METADATA
django_turnstile-0.1.3.dist-info/WHEEL
django_turnstile-0.1.3.dist-info/top_level.txt
django_turnstile-0.1.3.dist-info/RECORD
